{
  "uid": "om-frontend",
  "title": "OpenMentor · Frontend",
  "description": "Next.js frontend deep dive: SSR performance, page views, HTTP traffic, Node.js runtime and error logs.",
  "tags": [
    "openmentor"
  ],
  "timezone": "browser",
  "schemaVersion": 41,
  "refresh": "1m",
  "time": {
    "from": "now-6h",
    "to": "now"
  },
  "editable": true,
  "graphTooltip": 1,
  "fiscalYearStartMonth": 0,
  "preload": false,
  "links": [
    {
      "title": "OpenMentor dashboards",
      "type": "dashboards",
      "tags": [
        "openmentor"
      ],
      "asDropdown": true,
      "includeVars": false,
      "keepTime": true,
      "icon": "external link",
      "targetBlank": false,
      "url": ""
    }
  ],
  "templating": {
    "list": []
  },
  "annotations": {
    "list": [
      {
        "builtIn": 1,
        "datasource": {
          "type": "grafana",
          "uid": "-- Grafana --"
        },
        "enable": true,
        "hide": true,
        "iconColor": "rgba(0, 211, 255, 1)",
        "name": "Annotations & Alerts",
        "type": "dashboard"
      }
    ]
  },
  "panels": [
    {
      "type": "row",
      "title": "SSR & Page Views",
      "collapsed": false,
      "gridPos": {
        "h": 1,
        "w": 24,
        "x": 0,
        "y": 0
      },
      "id": 1,
      "panels": []
    },
    {
      "type": "timeseries",
      "title": "SSR Duration Percentiles",
      "description": "p50 / p95 / p99 Next.js server-side rendering duration across all pages.",
      "datasource": {
        "type": "prometheus",
        "uid": "grafanacloud-prom"
      },
      "targets": [
        {
          "datasource": {
            "type": "prometheus",
            "uid": "grafanacloud-prom"
          },
          "expr": "histogram_quantile(0.5, sum by (le) (rate(nextjs_ssr_duration_seconds_bucket{service_name=\"openmentor-frontend\"}[$__rate_interval])))",
          "refId": "A",
          "range": true,
          "instant": false,
          "editorMode": "code",
          "legendFormat": "p50"
        },
        {
          "datasource": {
            "type": "prometheus",
            "uid": "grafanacloud-prom"
          },
          "expr": "histogram_quantile(0.95, sum by (le) (rate(nextjs_ssr_duration_seconds_bucket{service_name=\"openmentor-frontend\"}[$__rate_interval])))",
          "refId": "B",
          "range": true,
          "instant": false,
          "editorMode": "code",
          "legendFormat": "p95"
        },
        {
          "datasource": {
            "type": "prometheus",
            "uid": "grafanacloud-prom"
          },
          "expr": "histogram_quantile(0.99, sum by (le) (rate(nextjs_ssr_duration_seconds_bucket{service_name=\"openmentor-frontend\"}[$__rate_interval])))",
          "refId": "C",
          "range": true,
          "instant": false,
          "editorMode": "code",
          "legendFormat": "p99"
        }
      ],
      "fieldConfig": {
        "defaults": {
          "color": {
            "mode": "palette-classic"
          },
          "unit": "s",
          "min": 0,
          "custom": {
            "drawStyle": "line",
            "lineWidth": 2,
            "fillOpacity": 10,
            "showPoints": "never",
            "pointSize": 5,
            "spanNulls": false,
            "axisBorderShow": false,
            "axisCenteredZero": false,
            "axisColorMode": "text",
            "axisLabel": "",
            "axisPlacement": "auto",
            "barAlignment": 0,
            "gradientMode": "none",
            "insertNulls": false,
            "lineInterpolation": "linear",
            "scaleDistribution": {
              "type": "linear"
            },
            "stacking": {
              "group": "A",
              "mode": "none"
            },
            "thresholdsStyle": {
              "mode": "off"
            },
            "hideFrom": {
              "legend": false,
              "tooltip": false,
              "viz": false
            }
          },
          "thresholds": {
            "mode": "absolute",
            "steps": [
              {
                "color": "green",
                "value": null
              }
            ]
          },
          "mappings": []
        },
        "overrides": []
      },
      "options": {
        "legend": {
          "calcs": [
            "mean",
            "max",
            "lastNotNull"
          ],
          "displayMode": "table",
          "placement": "bottom",
          "showLegend": true
        },
        "tooltip": {
          "mode": "multi",
          "sort": "desc"
        }
      },
      "id": 2,
      "gridPos": {
        "h": 8,
        "w": 8,
        "x": 0,
        "y": 1
      }
    },
    {
      "type": "timeseries",
      "title": "SSR p95 by Page",
      "description": "95th percentile SSR duration per page.",
      "datasource": {
        "type": "prometheus",
        "uid": "grafanacloud-prom"
      },
      "targets": [
        {
          "datasource": {
            "type": "prometheus",
            "uid": "grafanacloud-prom"
          },
          "expr": "histogram_quantile(0.95, sum by (le, page) (rate(nextjs_ssr_duration_seconds_bucket{service_name=\"openmentor-frontend\"}[$__rate_interval])))",
          "refId": "A",
          "range": true,
          "instant": false,
          "editorMode": "code",
          "legendFormat": "{{page}}"
        }
      ],
      "fieldConfig": {
        "defaults": {
          "color": {
            "mode": "palette-classic"
          },
          "unit": "s",
          "min": 0,
          "custom": {
            "drawStyle": "line",
            "lineWidth": 2,
            "fillOpacity": 10,
            "showPoints": "never",
            "pointSize": 5,
            "spanNulls": false,
            "axisBorderShow": false,
            "axisCenteredZero": false,
            "axisColorMode": "text",
            "axisLabel": "",
            "axisPlacement": "auto",
            "barAlignment": 0,
            "gradientMode": "none",
            "insertNulls": false,
            "lineInterpolation": "linear",
            "scaleDistribution": {
              "type": "linear"
            },
            "stacking": {
              "group": "A",
              "mode": "none"
            },
            "thresholdsStyle": {
              "mode": "off"
            },
            "hideFrom": {
              "legend": false,
              "tooltip": false,
              "viz": false
            }
          },
          "thresholds": {
            "mode": "absolute",
            "steps": [
              {
                "color": "green",
                "value": null
              }
            ]
          },
          "mappings": []
        },
        "overrides": []
      },
      "options": {
        "legend": {
          "calcs": [
            "mean",
            "max",
            "lastNotNull"
          ],
          "displayMode": "table",
          "placement": "bottom",
          "showLegend": true
        },
        "tooltip": {
          "mode": "multi",
          "sort": "desc"
        }
      },
      "id": 3,
      "gridPos": {
        "h": 8,
        "w": 8,
        "x": 8,
        "y": 1
      }
    },
    {
      "type": "timeseries",
      "title": "Page Views by Page",
      "description": "Server-rendered page views per second, split by page.",
      "datasource": {
        "type": "prometheus",
        "uid": "grafanacloud-prom"
      },
      "targets": [
        {
          "datasource": {
            "type": "prometheus",
            "uid": "grafanacloud-prom"
          },
          "expr": "sum by (page) (rate(nextjs_page_views_total{service_name=\"openmentor-frontend\"}[$__rate_interval]))",
          "refId": "A",
          "range": true,
          "instant": false,
          "editorMode": "code",
          "legendFormat": "{{page}}"
        }
      ],
      "fieldConfig": {
        "defaults": {
          "color": {
            "mode": "palette-classic"
          },
          "unit": "reqps",
          "min": 0,
          "custom": {
            "drawStyle": "line",
            "lineWidth": 2,
            "fillOpacity": 10,
            "showPoints": "never",
            "pointSize": 5,
            "spanNulls": false,
            "axisBorderShow": false,
            "axisCenteredZero": false,
            "axisColorMode": "text",
            "axisLabel": "",
            "axisPlacement": "auto",
            "barAlignment": 0,
            "gradientMode": "none",
            "insertNulls": false,
            "lineInterpolation": "linear",
            "scaleDistribution": {
              "type": "linear"
            },
            "stacking": {
              "group": "A",
              "mode": "none"
            },
            "thresholdsStyle": {
              "mode": "off"
            },
            "hideFrom": {
              "legend": false,
              "tooltip": false,
              "viz": false
            }
          },
          "thresholds": {
            "mode": "absolute",
            "steps": [
              {
                "color": "green",
                "value": null
              }
            ]
          },
          "mappings": []
        },
        "overrides": []
      },
      "options": {
        "legend": {
          "calcs": [
            "mean",
            "max",
            "lastNotNull"
          ],
          "displayMode": "table",
          "placement": "bottom",
          "showLegend": true
        },
        "tooltip": {
          "mode": "multi",
          "sort": "desc"
        }
      },
      "id": 4,
      "gridPos": {
        "h": 8,
        "w": 8,
        "x": 16,
        "y": 1
      }
    },
    {
      "type": "row",
      "title": "HTTP",
      "collapsed": false,
      "gridPos": {
        "h": 1,
        "w": 24,
        "x": 0,
        "y": 9
      },
      "id": 5,
      "panels": []
    },
    {
      "type": "timeseries",
      "title": "Request Rate by Route",
      "description": "HTTP requests per second on the frontend, top 10 routes.",
      "datasource": {
        "type": "prometheus",
        "uid": "grafanacloud-prom"
      },
      "targets": [
        {
          "datasource": {
            "type": "prometheus",
            "uid": "grafanacloud-prom"
          },
          "expr": "topk(10, sum by (http_route) (rate(http_server_request_total{service_name=\"openmentor-frontend\"}[$__rate_interval])))",
          "refId": "A",
          "range": true,
          "instant": false,
          "editorMode": "code",
          "legendFormat": "{{http_route}}"
        }
      ],
      "fieldConfig": {
        "defaults": {
          "color": {
            "mode": "palette-classic"
          },
          "unit": "reqps",
          "min": 0,
          "custom": {
            "drawStyle": "line",
            "lineWidth": 2,
            "fillOpacity": 10,
            "showPoints": "never",
            "pointSize": 5,
            "spanNulls": false,
            "axisBorderShow": false,
            "axisCenteredZero": false,
            "axisColorMode": "text",
            "axisLabel": "",
            "axisPlacement": "auto",
            "barAlignment": 0,
            "gradientMode": "none",
            "insertNulls": false,
            "lineInterpolation": "linear",
            "scaleDistribution": {
              "type": "linear"
            },
            "stacking": {
              "group": "A",
              "mode": "none"
            },
            "thresholdsStyle": {
              "mode": "off"
            },
            "hideFrom": {
              "legend": false,
              "tooltip": false,
              "viz": false
            }
          },
          "thresholds": {
            "mode": "absolute",
            "steps": [
              {
                "color": "green",
                "value": null
              }
            ]
          },
          "mappings": []
        },
        "overrides": []
      },
      "options": {
        "legend": {
          "calcs": [
            "mean",
            "max",
            "lastNotNull"
          ],
          "displayMode": "table",
          "placement": "bottom",
          "showLegend": true
        },
        "tooltip": {
          "mode": "multi",
          "sort": "desc"
        }
      },
      "id": 6,
      "gridPos": {
        "h": 8,
        "w": 6,
        "x": 0,
        "y": 10
      }
    },
    {
      "type": "timeseries",
      "title": "Responses by Status Code",
      "description": "HTTP responses per second by status code.",
      "datasource": {
        "type": "prometheus",
        "uid": "grafanacloud-prom"
      },
      "targets": [
        {
          "datasource": {
            "type": "prometheus",
            "uid": "grafanacloud-prom"
          },
          "expr": "sum by (http_response_status_code) (rate(http_server_request_total{service_name=\"openmentor-frontend\"}[$__rate_interval]))",
          "refId": "A",
          "range": true,
          "instant": false,
          "editorMode": "code",
          "legendFormat": "{{http_response_status_code}}"
        }
      ],
      "fieldConfig": {
        "defaults": {
          "color": {
            "mode": "palette-classic"
          },
          "unit": "reqps",
          "min": 0,
          "custom": {
            "drawStyle": "line",
            "lineWidth": 2,
            "fillOpacity": 10,
            "showPoints": "never",
            "pointSize": 5,
            "spanNulls": false,
            "axisBorderShow": false,
            "axisCenteredZero": false,
            "axisColorMode": "text",
            "axisLabel": "",
            "axisPlacement": "auto",
            "barAlignment": 0,
            "gradientMode": "none",
            "insertNulls": false,
            "lineInterpolation": "linear",
            "scaleDistribution": {
              "type": "linear"
            },
            "stacking": {
              "group": "A",
              "mode": "none"
            },
            "thresholdsStyle": {
              "mode": "off"
            },
            "hideFrom": {
              "legend": false,
              "tooltip": false,
              "viz": false
            }
          },
          "thresholds": {
            "mode": "absolute",
            "steps": [
              {
                "color": "green",
                "value": null
              }
            ]
          },
          "mappings": []
        },
        "overrides": []
      },
      "options": {
        "legend": {
          "calcs": [
            "mean",
            "max",
            "lastNotNull"
          ],
          "displayMode": "table",
          "placement": "bottom",
          "showLegend": true
        },
        "tooltip": {
          "mode": "multi",
          "sort": "desc"
        }
      },
      "id": 7,
      "gridPos": {
        "h": 8,
        "w": 6,
        "x": 6,
        "y": 10
      }
    },
    {
      "type": "timeseries",
      "title": "Latency Percentiles",
      "description": "p50 / p95 / p99 HTTP request duration on the frontend.",
      "datasource": {
        "type": "prometheus",
        "uid": "grafanacloud-prom"
      },
      "targets": [
        {
          "datasource": {
            "type": "prometheus",
            "uid": "grafanacloud-prom"
          },
          "expr": "histogram_quantile(0.5, sum by (le) (rate(http_server_request_duration_seconds_bucket{service_name=\"openmentor-frontend\"}[$__rate_interval])))",
          "refId": "A",
          "range": true,
          "instant": false,
          "editorMode": "code",
          "legendFormat": "p50"
        },
        {
          "datasource": {
            "type": "prometheus",
            "uid": "grafanacloud-prom"
          },
          "expr": "histogram_quantile(0.95, sum by (le) (rate(http_server_request_duration_seconds_bucket{service_name=\"openmentor-frontend\"}[$__rate_interval])))",
          "refId": "B",
          "range": true,
          "instant": false,
          "editorMode": "code",
          "legendFormat": "p95"
        },
        {
          "datasource": {
            "type": "prometheus",
            "uid": "grafanacloud-prom"
          },
          "expr": "histogram_quantile(0.99, sum by (le) (rate(http_server_request_duration_seconds_bucket{service_name=\"openmentor-frontend\"}[$__rate_interval])))",
          "refId": "C",
          "range": true,
          "instant": false,
          "editorMode": "code",
          "legendFormat": "p99"
        }
      ],
      "fieldConfig": {
        "defaults": {
          "color": {
            "mode": "palette-classic"
          },
          "unit": "s",
          "min": 0,
          "custom": {
            "drawStyle": "line",
            "lineWidth": 2,
            "fillOpacity": 10,
            "showPoints": "never",
            "pointSize": 5,
            "spanNulls": false,
            "axisBorderShow": false,
            "axisCenteredZero": false,
            "axisColorMode": "text",
            "axisLabel": "",
            "axisPlacement": "auto",
            "barAlignment": 0,
            "gradientMode": "none",
            "insertNulls": false,
            "lineInterpolation": "linear",
            "scaleDistribution": {
              "type": "linear"
            },
            "stacking": {
              "group": "A",
              "mode": "none"
            },
            "thresholdsStyle": {
              "mode": "off"
            },
            "hideFrom": {
              "legend": false,
              "tooltip": false,
              "viz": false
            }
          },
          "thresholds": {
            "mode": "absolute",
            "steps": [
              {
                "color": "green",
                "value": null
              }
            ]
          },
          "mappings": []
        },
        "overrides": []
      },
      "options": {
        "legend": {
          "calcs": [
            "mean",
            "max",
            "lastNotNull"
          ],
          "displayMode": "table",
          "placement": "bottom",
          "showLegend": true
        },
        "tooltip": {
          "mode": "multi",
          "sort": "desc"
        }
      },
      "id": 8,
      "gridPos": {
        "h": 8,
        "w": 6,
        "x": 12,
        "y": 10
      }
    },
    {
      "type": "timeseries",
      "title": "Mentor Profile Views",
      "description": "Mentor profile page views per second (frontend business metric).",
      "datasource": {
        "type": "prometheus",
        "uid": "grafanacloud-prom"
      },
      "targets": [
        {
          "datasource": {
            "type": "prometheus",
            "uid": "grafanacloud-prom"
          },
          "expr": "sum(rate(openmentor_mentor_profile_views_total{service_name=\"openmentor-frontend\"}[$__rate_interval]))",
          "refId": "A",
          "range": true,
          "instant": false,
          "editorMode": "code",
          "legendFormat": "profile views"
        }
      ],
      "fieldConfig": {
        "defaults": {
          "color": {
            "mode": "palette-classic"
          },
          "unit": "reqps",
          "min": 0,
          "custom": {
            "drawStyle": "line",
            "lineWidth": 2,
            "fillOpacity": 10,
            "showPoints": "never",
            "pointSize": 5,
            "spanNulls": false,
            "axisBorderShow": false,
            "axisCenteredZero": false,
            "axisColorMode": "text",
            "axisLabel": "",
            "axisPlacement": "auto",
            "barAlignment": 0,
            "gradientMode": "none",
            "insertNulls": false,
            "lineInterpolation": "linear",
            "scaleDistribution": {
              "type": "linear"
            },
            "stacking": {
              "group": "A",
              "mode": "none"
            },
            "thresholdsStyle": {
              "mode": "off"
            },
            "hideFrom": {
              "legend": false,
              "tooltip": false,
              "viz": false
            }
          },
          "thresholds": {
            "mode": "absolute",
            "steps": [
              {
                "color": "green",
                "value": null
              }
            ]
          },
          "mappings": []
        },
        "overrides": []
      },
      "options": {
        "legend": {
          "calcs": [
            "mean",
            "max",
            "lastNotNull"
          ],
          "displayMode": "table",
          "placement": "bottom",
          "showLegend": true
        },
        "tooltip": {
          "mode": "multi",
          "sort": "desc"
        }
      },
      "id": 9,
      "gridPos": {
        "h": 8,
        "w": 6,
        "x": 18,
        "y": 10
      }
    },
    {
      "type": "row",
      "title": "Node.js Runtime",
      "collapsed": true,
      "gridPos": {
        "h": 1,
        "w": 24,
        "x": 0,
        "y": 18
      },
      "id": 10,
      "panels": [
        {
          "type": "timeseries",
          "title": "Event Loop Lag",
          "description": "Node.js event loop lag percentiles; sustained values above 100ms indicate a blocked event loop.",
          "datasource": {
            "type": "prometheus",
            "uid": "grafanacloud-prom"
          },
          "targets": [
            {
              "datasource": {
                "type": "prometheus",
                "uid": "grafanacloud-prom"
              },
              "expr": "nodejs_eventloop_lag_p50_seconds{service_name=\"openmentor-frontend\"}",
              "refId": "A",
              "range": true,
              "instant": false,
              "editorMode": "code",
              "legendFormat": "p50"
            },
            {
              "datasource": {
                "type": "prometheus",
                "uid": "grafanacloud-prom"
              },
              "expr": "nodejs_eventloop_lag_p99_seconds{service_name=\"openmentor-frontend\"}",
              "refId": "B",
              "range": true,
              "instant": false,
              "editorMode": "code",
              "legendFormat": "p99"
            },
            {
              "datasource": {
                "type": "prometheus",
                "uid": "grafanacloud-prom"
              },
              "expr": "nodejs_eventloop_lag_mean_seconds{service_name=\"openmentor-frontend\"}",
              "refId": "C",
              "range": true,
              "instant": false,
              "editorMode": "code",
              "legendFormat": "mean"
            }
          ],
          "fieldConfig": {
            "defaults": {
              "color": {
                "mode": "palette-classic"
              },
              "unit": "s",
              "min": 0,
              "custom": {
                "drawStyle": "line",
                "lineWidth": 2,
                "fillOpacity": 10,
                "showPoints": "never",
                "pointSize": 5,
                "spanNulls": false,
                "axisBorderShow": false,
                "axisCenteredZero": false,
                "axisColorMode": "text",
                "axisLabel": "",
                "axisPlacement": "auto",
                "barAlignment": 0,
                "gradientMode": "none",
                "insertNulls": false,
                "lineInterpolation": "linear",
                "scaleDistribution": {
                  "type": "linear"
                },
                "stacking": {
                  "group": "A",
                  "mode": "none"
                },
                "thresholdsStyle": {
                  "mode": "dashed"
                },
                "hideFrom": {
                  "legend": false,
                  "tooltip": false,
                  "viz": false
                }
              },
              "thresholds": {
                "mode": "absolute",
                "steps": [
                  {
                    "color": "green",
                    "value": null
                  },
                  {
                    "color": "red",
                    "value": 0.1
                  }
                ]
              },
              "mappings": []
            },
            "overrides": []
          },
          "options": {
            "legend": {
              "calcs": [
                "mean",
                "max",
                "lastNotNull"
              ],
              "displayMode": "table",
              "placement": "bottom",
              "showLegend": true
            },
            "tooltip": {
              "mode": "multi",
              "sort": "desc"
            }
          },
          "id": 11,
          "gridPos": {
            "h": 8,
            "w": 6,
            "x": 0,
            "y": 19
          }
        },
        {
          "type": "timeseries",
          "title": "Heap Usage",
          "description": "V8 heap used vs total, plus external memory.",
          "datasource": {
            "type": "prometheus",
            "uid": "grafanacloud-prom"
          },
          "targets": [
            {
              "datasource": {
                "type": "prometheus",
                "uid": "grafanacloud-prom"
              },
              "expr": "nodejs_heap_size_used_bytes{service_name=\"openmentor-frontend\"}",
              "refId": "A",
              "range": true,
              "instant": false,
              "editorMode": "code",
              "legendFormat": "heap used"
            },
            {
              "datasource": {
                "type": "prometheus",
                "uid": "grafanacloud-prom"
              },
              "expr": "nodejs_heap_size_total_bytes{service_name=\"openmentor-frontend\"}",
              "refId": "B",
              "range": true,
              "instant": false,
              "editorMode": "code",
              "legendFormat": "heap total"
            },
            {
              "datasource": {
                "type": "prometheus",
                "uid": "grafanacloud-prom"
              },
              "expr": "nodejs_external_memory_bytes{service_name=\"openmentor-frontend\"}",
              "refId": "C",
              "range": true,
              "instant": false,
              "editorMode": "code",
              "legendFormat": "external"
            }
          ],
          "fieldConfig": {
            "defaults": {
              "color": {
                "mode": "palette-classic"
              },
              "unit": "bytes",
              "min": 0,
              "custom": {
                "drawStyle": "line",
                "lineWidth": 2,
                "fillOpacity": 10,
                "showPoints": "never",
                "pointSize": 5,
                "spanNulls": false,
                "axisBorderShow": false,
                "axisCenteredZero": false,
                "axisColorMode": "text",
                "axisLabel": "",
                "axisPlacement": "auto",
                "barAlignment": 0,
                "gradientMode": "none",
                "insertNulls": false,
                "lineInterpolation": "linear",
                "scaleDistribution": {
                  "type": "linear"
                },
                "stacking": {
                  "group": "A",
                  "mode": "none"
                },
                "thresholdsStyle": {
                  "mode": "off"
                },
                "hideFrom": {
                  "legend": false,
                  "tooltip": false,
                  "viz": false
                }
              },
              "thresholds": {
                "mode": "absolute",
                "steps": [
                  {
                    "color": "green",
                    "value": null
                  }
                ]
              },
              "mappings": []
            },
            "overrides": []
          },
          "options": {
            "legend": {
              "calcs": [
                "mean",
                "max",
                "lastNotNull"
              ],
              "displayMode": "table",
              "placement": "bottom",
              "showLegend": true
            },
            "tooltip": {
              "mode": "multi",
              "sort": "desc"
            }
          },
          "id": 12,
          "gridPos": {
            "h": 8,
            "w": 6,
            "x": 6,
            "y": 19
          }
        },
        {
          "type": "timeseries",
          "title": "GC Time by Kind",
          "description": "Seconds per second spent in garbage collection, by GC kind.",
          "datasource": {
            "type": "prometheus",
            "uid": "grafanacloud-prom"
          },
          "targets": [
            {
              "datasource": {
                "type": "prometheus",
                "uid": "grafanacloud-prom"
              },
              "expr": "sum by (kind) (rate(nodejs_gc_duration_seconds_sum{service_name=\"openmentor-frontend\"}[$__rate_interval]))",
              "refId": "A",
              "range": true,
              "instant": false,
              "editorMode": "code",
              "legendFormat": "{{kind}}"
            }
          ],
          "fieldConfig": {
            "defaults": {
              "color": {
                "mode": "palette-classic"
              },
              "unit": "percentunit",
              "min": 0,
              "custom": {
                "drawStyle": "line",
                "lineWidth": 2,
                "fillOpacity": 10,
                "showPoints": "never",
                "pointSize": 5,
                "spanNulls": false,
                "axisBorderShow": false,
                "axisCenteredZero": false,
                "axisColorMode": "text",
                "axisLabel": "",
                "axisPlacement": "auto",
                "barAlignment": 0,
                "gradientMode": "none",
                "insertNulls": false,
                "lineInterpolation": "linear",
                "scaleDistribution": {
                  "type": "linear"
                },
                "stacking": {
                  "group": "A",
                  "mode": "none"
                },
                "thresholdsStyle": {
                  "mode": "off"
                },
                "hideFrom": {
                  "legend": false,
                  "tooltip": false,
                  "viz": false
                }
              },
              "thresholds": {
                "mode": "absolute",
                "steps": [
                  {
                    "color": "green",
                    "value": null
                  }
                ]
              },
              "mappings": []
            },
            "overrides": []
          },
          "options": {
            "legend": {
              "calcs": [
                "mean",
                "max",
                "lastNotNull"
              ],
              "displayMode": "table",
              "placement": "bottom",
              "showLegend": true
            },
            "tooltip": {
              "mode": "multi",
              "sort": "desc"
            }
          },
          "id": 13,
          "gridPos": {
            "h": 8,
            "w": 6,
            "x": 12,
            "y": 19
          }
        },
        {
          "type": "timeseries",
          "title": "Process CPU & RSS",
          "description": "Process CPU usage and resident memory of the Next.js process.",
          "datasource": {
            "type": "prometheus",
            "uid": "grafanacloud-prom"
          },
          "targets": [
            {
              "datasource": {
                "type": "prometheus",
                "uid": "grafanacloud-prom"
              },
              "expr": "rate(process_cpu_seconds_total{service_name=\"openmentor-frontend\"}[$__rate_interval]) * 100",
              "refId": "A",
              "range": true,
              "instant": false,
              "editorMode": "code",
              "legendFormat": "CPU %"
            },
            {
              "datasource": {
                "type": "prometheus",
                "uid": "grafanacloud-prom"
              },
              "expr": "process_resident_memory_bytes{service_name=\"openmentor-frontend\"}",
              "refId": "B",
              "range": true,
              "instant": false,
              "editorMode": "code",
              "legendFormat": "RSS"
            }
          ],
          "fieldConfig": {
            "defaults": {
              "color": {
                "mode": "palette-classic"
              },
              "unit": "short",
              "min": 0,
              "custom": {
                "drawStyle": "line",
                "lineWidth": 2,
                "fillOpacity": 10,
                "showPoints": "never",
                "pointSize": 5,
                "spanNulls": false,
                "axisBorderShow": false,
                "axisCenteredZero": false,
                "axisColorMode": "text",
                "axisLabel": "",
                "axisPlacement": "auto",
                "barAlignment": 0,
                "gradientMode": "none",
                "insertNulls": false,
                "lineInterpolation": "linear",
                "scaleDistribution": {
                  "type": "linear"
                },
                "stacking": {
                  "group": "A",
                  "mode": "none"
                },
                "thresholdsStyle": {
                  "mode": "off"
                },
                "hideFrom": {
                  "legend": false,
                  "tooltip": false,
                  "viz": false
                }
              },
              "thresholds": {
                "mode": "absolute",
                "steps": [
                  {
                    "color": "green",
                    "value": null
                  }
                ]
              },
              "mappings": []
            },
            "overrides": [
              {
                "matcher": {
                  "id": "byName",
                  "options": "RSS"
                },
                "properties": [
                  {
                    "id": "unit",
                    "value": "bytes"
                  },
                  {
                    "id": "custom.axisPlacement",
                    "value": "right"
                  }
                ]
              }
            ]
          },
          "options": {
            "legend": {
              "calcs": [
                "mean",
                "max",
                "lastNotNull"
              ],
              "displayMode": "table",
              "placement": "bottom",
              "showLegend": true
            },
            "tooltip": {
              "mode": "multi",
              "sort": "desc"
            }
          },
          "id": 14,
          "gridPos": {
            "h": 8,
            "w": 6,
            "x": 18,
            "y": 19
          }
        }
      ]
    },
    {
      "type": "row",
      "title": "Logs",
      "collapsed": true,
      "gridPos": {
        "h": 1,
        "w": 24,
        "x": 0,
        "y": 19
      },
      "id": 15,
      "panels": [
        {
          "type": "logs",
          "title": "Frontend Error Logs",
          "description": "Most recent error-level log lines from the Next.js frontend.",
          "datasource": {
            "type": "loki",
            "uid": "grafanacloud-logs"
          },
          "targets": [
            {
              "datasource": {
                "type": "loki",
                "uid": "grafanacloud-logs"
              },
              "expr": "{service_name=\"openmentor-frontend\"} | level = `error`",
              "refId": "A",
              "queryType": "range"
            }
          ],
          "options": {
            "showTime": true,
            "showLabels": false,
            "showCommonLabels": false,
            "wrapLogMessage": true,
            "prettifyLogMessage": false,
            "enableLogDetails": true,
            "dedupStrategy": "none",
            "sortOrder": "Descending"
          },
          "fieldConfig": {
            "defaults": {},
            "overrides": []
          },
          "id": 16,
          "gridPos": {
            "h": 10,
            "w": 24,
            "x": 0,
            "y": 20
          }
        }
      ]
    }
  ]
}
